[
    {
        "id": "SELECT",
        "expreg": "SELECT"
    },
    {
        "id": "WHERE",
        "expreg": "WHERE"
    },
    {
        "id": "LIMIT",
        "expreg": "LIMIT"
    },
    {
        "id": "VARIABLE",
        "expreg": "\\?\\w+"
    },
    {
        "id": "STRING",
        "expreg": "\"[^\"]+\"@\\w+"
    },
    {
        "id": "URI",
        "expreg": "\\w+:\\w+"
    },
    {
        "id": "DOT",
        "expreg": "\\."
    },
    {
        "id": "LBRACE",
        "expreg": "\\{"
    },
    {
        "id": "RBRACE",
        "expreg": "\\}"
    },
    {
        "id": "A",
        "expreg": "a"
    },
    {
        "id": "SKIP",
        "expreg": "\\s+"
    },
    {
        "id": "COMMENT",
        "expreg": "#[^\\n]*"
    }
]